key_sdk/__init__.py
key_sdk/aes.py
key_sdk/client.py
key_sdk/logger.py
key_sdk/rsa.py
key_sdk/secret.py
key_sdk/utils.py
keyvault_sdk-0.1.3.dist-info/METADATA
keyvault_sdk-0.1.3.dist-info/WHEEL
keyvault_sdk-0.1.3.dist-info/top_level.txt
keyvault_sdk-0.1.3.dist-info/RECORD
