Metadata-Version: 2.2
Name: keyvault-sdk
Version: 0.1.3
Summary: 密钥管理SDK-0.1.3:添加记录解密日志功能
Author: single.wong
Author-email: wongsingle@163.com
Classifier: Programming Language :: Python :: 3
Classifier: License :: OSI Approved :: MIT License
Classifier: Operating System :: OS Independent
Requires-Python: >=3.7.5
Requires-Dist: requests
Requires-Dist: pycryptodome
Requires-Dist: apscheduler
Requires-Dist: loguru
Dynamic: author
Dynamic: author-email
Dynamic: classifier
Dynamic: description
Dynamic: description-content-type
Dynamic: requires-dist
Dynamic: requires-python
Dynamic: summary
